basemkit/__init__.py
basemkit/argparse_action.py
basemkit/base_cmd.py
basemkit/basetest.py
basemkit/docker_util.py
basemkit/persistent_log.py
basemkit/profiler.py
basemkit/remotedebug.py
basemkit/shell.py
basemkit/yamlable.py
pybasemkit-0.2.0.dist-info/METADATA
pybasemkit-0.2.0.dist-info/WHEEL
pybasemkit-0.2.0.dist-info/licenses/LICENSE
pybasemkit-0.2.0.dist-info/RECORD
