Metadata-Version: 2.4
Name: pybasemkit
Version: 0.2.0
Summary: Python base module kit: YAML/JSON I/O, structured logging, CLI tooling, shell execution, and pydevd remote debug support.
Project-URL: Home, https://github.com/WolfgangFahl/pybasemkit
Project-URL: Documentation, https://wiki.bitplan.com/index.php/pybasemkit
Project-URL: Source, https://github.com/WolfgangFahl/pybasemkit
Author-email: Wolfgang Fahl <wf@WolfgangFahl.com>
Maintainer-email: Wolfgang Fahl <wf@WolfgangFahl.com>
License: Apache-2.0
License-File: LICENSE
Keywords: cli,dataclass,debug,infrastructure,logging,shell,yaml
Classifier: Development Status :: 4 - Beta
Classifier: Intended Audience :: Developers
Classifier: License :: OSI Approved :: Apache Software License
Classifier: Operating System :: OS Independent
Classifier: Programming Language :: Python :: 3 :: Only
Classifier: Programming Language :: Python :: 3.10
Classifier: Programming Language :: Python :: 3.11
Classifier: Programming Language :: Python :: 3.12
Classifier: Programming Language :: Python :: 3.13
Classifier: Topic :: Software Development :: Libraries :: Python Modules
Requires-Python: >=3.10
Requires-Dist: dacite>=1.9.2
Requires-Dist: dataclasses-json>=0.6.7
Requires-Dist: pyyaml>=6.0.2
Requires-Dist: shutup>=0.2.0
Provides-Extra: dev
Requires-Dist: black>=25.1.0; extra == 'dev'
Requires-Dist: isort>=6.0.1; extra == 'dev'
Provides-Extra: test
Requires-Dist: green>=3.3.0; extra == 'test'
Requires-Dist: pytest>=8.4.0; extra == 'test'
Requires-Dist: tox>=4.15.0; extra == 'test'
